gdbPy/__init__.py
gdbPy/basics.py
gdbPy/breakpoint.py
gdbPy/execution.py
gdbPy/info.py
gdbPy/signals.py
gdbPy-0.1.2.dist-info/LICENSE
gdbPy-0.1.2.dist-info/METADATA
gdbPy-0.1.2.dist-info/WHEEL
gdbPy-0.1.2.dist-info/top_level.txt
gdbPy-0.1.2.dist-info/RECORD
