Metadata-Version: 2.1
Name: gdbPy
Version: 0.1.2
Summary: gdb scripts in Python
Home-page: https://github.com/MarcoBalossini/gdbPy
Author: Marco Balossini
License: GPL
Keywords: gdb,debugging
Platform: UNKNOWN
Classifier: Intended Audience :: Developers
Classifier: License :: OSI Approved :: GNU General Public License v3 or later (GPLv3+)
Classifier: Programming Language :: Python :: 3
